MoleCool/Bfield.py
MoleCool/Lasersystem.py
MoleCool/Levelsystem.py
MoleCool/System.py
MoleCool/__init__.py
MoleCool/_version.py
MoleCool/run_examples.py
MoleCool/spectra.py
MoleCool/Examples/core/BCF.py
MoleCool/Examples/core/GALLERY_HEADER.rst
MoleCool/Examples/core/YbOH.py
MoleCool/Examples/core/chirp_slowing.py
MoleCool/Examples/core/cooling_forces.py
MoleCool/Examples/core/cooling_forces_RaF.py
MoleCool/Examples/core/optcycl_12+4levels.py
MoleCool/Examples/core/optcycl_3+1levels.py
MoleCool/Examples/core/plot_EIT.py
MoleCool/Examples/core/plot_RabiOsci_2level.py
MoleCool/Examples/core/plot_spectra_RaF.py
MoleCool/Examples/misc/GALLERY_HEADER.rst
MoleCool/Examples/misc/plot_Simple3+1.py
MoleCool/Examples/misc/plot_SimpleTest1_BaF.py
MoleCool/Examples/misc/plot_SimpleTest2Traj_BaF.py
MoleCool/Examples/misc/plot_getting_started.py
MoleCool/constants/137BaF.json
MoleCool/constants/138BaF.json
MoleCool/constants/171YbOH.json
MoleCool/constants/226RaF.json
MoleCool/constants/CaF.json
MoleCool/tools/ODEs.py
MoleCool/tools/__init__.py
MoleCool/tools/dict2DF.py
MoleCool/tools/diststraj.py
molecool-3.7.3.dist-info/licenses/LICENSE.md
molecool-3.7.3.dist-info/METADATA
molecool-3.7.3.dist-info/WHEEL
molecool-3.7.3.dist-info/top_level.txt
molecool-3.7.3.dist-info/RECORD
