Metadata-Version: 2.4
Name: MoleCool
Version: 3.7.3
Summary: Molecular Laser-Cooling and Spectra Simulation
Author-email: Felix Kogel <felix.kogel@t-online.de>
License-Expression: MIT
Project-URL: Homepage, https://www.coldmolecules.eu/Home/
Project-URL: Documentation, https://molecool-py.readthedocs.io/en/stable
Project-URL: Repository, https://github.com/LangenGroup/MoleCool
Project-URL: Issues, https://github.com/LangenGroup/MoleCool/issues
Keywords: cold molecules,laser cooling,optical Bloch equations,rate equations,diatomic molecules,multi-level systems,Rabi-oscillations,coherent laser forces
Classifier: Development Status :: 4 - Beta
Classifier: Intended Audience :: Science/Research
Classifier: Natural Language :: English
Classifier: Operating System :: OS Independent
Classifier: Programming Language :: Python :: 3
Classifier: Programming Language :: Python :: 3.8
Classifier: Topic :: Scientific/Engineering :: Physics
Requires-Python: >=3.8
License-File: LICENSE.md
Requires-Dist: numpy<2.0
Requires-Dist: numba>=0.53.1
Requires-Dist: pandas<1.4
Requires-Dist: scipy>=1.5.4
Requires-Dist: sympy<1.13
Requires-Dist: tqdm
Requires-Dist: matplotlib
Requires-Dist: h5py
Provides-Extra: doc
Requires-Dist: sphinx; extra == "doc"
Requires-Dist: sphinx-book-theme; extra == "doc"
Requires-Dist: sphinx-gallery; extra == "doc"
Requires-Dist: sphinx-copybutton; extra == "doc"
Requires-Dist: sphinx-design; extra == "doc"
Requires-Dist: sphinx-exec-code; extra == "doc"
Provides-Extra: dev
Requires-Dist: setuptools>=42; extra == "dev"
Requires-Dist: wheel; extra == "dev"
Requires-Dist: setuptools-scm; extra == "dev"
Requires-Dist: build; extra == "dev"
Requires-Dist: twine; extra == "dev"
Dynamic: license-file
